phase_o_matic/__init__.py
phase_o_matic/download.py
phase_o_matic/phase_delay.py
phase_o_matic/preprocess.py
phase_o_matic/presto.py
phase_o_matic/utils.py
phase_o_matic-0.1.0.dist-info/LICENSE
phase_o_matic-0.1.0.dist-info/METADATA
phase_o_matic-0.1.0.dist-info/WHEEL
phase_o_matic-0.1.0.dist-info/top_level.txt
phase_o_matic-0.1.0.dist-info/RECORD
