Metadata-Version: 2.1
Name: phase-o-matic
Version: 0.1.0
Summary: InSAR Atmospheric Delay Corrections with ERA5.
Home-page: https://github.com/ZachKeskinen/phase-o-matic
Author: Zach Keskinen
Author-email: zachkeskinen@gmail.com
License: MIT
Classifier: License :: OSI Approved :: MIT License
Classifier: Programming Language :: Python
Classifier: Programming Language :: Python :: 3
Classifier: Programming Language :: Python :: 3.7
Classifier: Programming Language :: Python :: Implementation :: CPython
Classifier: Programming Language :: Python :: Implementation :: PyPy
Requires-Python: >=3.7.0
License-File: LICENSE
Requires-Dist: numpy
Requires-Dist: pandas
Requires-Dist: xarray
Requires-Dist: rioxarray
Requires-Dist: shapely
Requires-Dist: cdsapi
Requires-Dist: scipy
